README.md
setup.py
cheesefactory_sftp/__init__.py
cheesefactory_sftp/connection.py
cheesefactory_sftp/exceptions.py
cheesefactory_sftp/get.py
cheesefactory_sftp/log.py
cheesefactory_sftp/put.py
cheesefactory_sftp/transfer.py
cheesefactory_sftp/transfer_list.py
cheesefactory_sftp/utilities.py
cheesefactory_sftp.egg-info/PKG-INFO
cheesefactory_sftp.egg-info/SOURCES.txt
cheesefactory_sftp.egg-info/dependency_links.txt
cheesefactory_sftp.egg-info/requires.txt
cheesefactory_sftp.egg-info/top_level.txt